LICENSE
README.md
pyproject.toml
setup.cfg
setup.py
jupyter_ai_wekeo/__init__.py
jupyter_ai_wekeo/llm.py
jupyter_ai_wekeo/provider.py
jupyter_ai_wekeo/slash_command.py
jupyter_ai_wekeo.egg-info/PKG-INFO
jupyter_ai_wekeo.egg-info/SOURCES.txt
jupyter_ai_wekeo.egg-info/dependency_links.txt
jupyter_ai_wekeo.egg-info/entry_points.txt
jupyter_ai_wekeo.egg-info/requires.txt
jupyter_ai_wekeo.egg-info/top_level.txt
jupyter_ai_wekeo/tests/__init__.py