Metadata-Version: 2.4
Name: jupyter_ai_wekeo
Version: 0.1.4
Summary: A Jupyter AI extension.
Author-email: test <test@mail.org>
License: BSD 3-Clause License
Classifier: Framework :: Jupyter
Classifier: Framework :: Jupyter :: JupyterLab
Classifier: Framework :: Jupyter :: JupyterLab :: 4
Classifier: License :: OSI Approved :: BSD License
Classifier: Programming Language :: Python
Classifier: Programming Language :: Python :: 3
Classifier: Programming Language :: Python :: 3.8
Classifier: Programming Language :: Python :: 3.9
Classifier: Programming Language :: Python :: 3.10
Classifier: Programming Language :: Python :: 3.11
Classifier: Programming Language :: Python :: 3.12
Requires-Python: >=3.8
License-File: LICENSE
Requires-Dist: jupyter_ai<2.29,>=2.23
Requires-Dist: langserve[client]<=0.2.3
Requires-Dist: fastapi
Requires-Dist: langchain-openai
Requires-Dist: httpx<0.28
Dynamic: license-file
